{"03400":{"cp":"03400","estado":"Ciudad de México","municipio":"Benito Juárez","colonias":["Álamos"],"coords":{"lat":19.40038681,"lon":-99.14099884}},"03410":{"cp":"03410","estado":"Ciudad de México","municipio":"Benito Juárez","colonias":["Postal"],"coords":{"lat":19.38994408,"lon":-99.14042664}},"03420":{"cp":"03420","estado":"Ciudad de México","municipio":"Benito Juárez","colonias":["Miguel Alemán"],"coords":{"lat":19.38962364,"lon":-99.14501953}},"03430":{"cp":"03430","estado":"Ciudad de México","municipio":"Benito Juárez","colonias":["Josefa Ortiz de Domínguez"],"coords":{"lat":19.38767815,"lon":-99.14112854}},"03440":{"cp":"03440","estado":"Ciudad de México","municipio":"Benito Juárez","colonias":["Niños Héroes"],"coords":{"lat":19.38631058,"lon":-99.14441681}}}