{"20000":{"cp":"20000","estado":"Aguascalientes","municipio":"Aguascalientes","colonias":["Aguascalientes Centro"],"coords":{"lat":21.88119125,"lon":-102.2961426}},"20010":{"cp":"20010","estado":"Aguascalientes","municipio":"Aguascalientes","colonias":["Colinas del Río","Olivares Santana","Las Brisas","Ramon Romo Franco","San Cayetano","Dominium"],"coords":{"lat":21.89402199,"lon":-102.3136063}},"20016":{"cp":"20016","estado":"Aguascalientes","municipio":"Aguascalientes","colonias":["Colinas de San Ignacio","La Fundición","Fundición II","Los Sauces"],"coords":{"lat":21.89860344,"lon":-102.3191147}},"20018":{"cp":"20018","estado":"Aguascalientes","municipio":"Aguascalientes","colonias":["Línea de Fuego"],"coords":{"lat":21.89938354,"lon":-102.3207626}},"20020":{"cp":"20020","estado":"Aguascalientes","municipio":"Aguascalientes","colonias":["Buenos Aires","Circunvalación Norte","Las Arboledas","Villas de San Francisco"],"coords":{"lat":21.89541435,"lon":-102.3056641}},"20029":{"cp":"20029","estado":"Aguascalientes","municipio":"Aguascalientes","colonias":["Villas de La Universidad"],"coords":{"lat":21.90048599,"lon":-102.305954}},"20030":{"cp":"20030","estado":"Aguascalientes","municipio":"Aguascalientes","colonias":["El Sol","Gremial","Industrial"],"coords":{"lat":21.89517975,"lon":-102.2968597}},"20040":{"cp":"20040","estado":"Aguascalientes","municipio":"Aguascalientes","colonias":["Altavista","Curtidores","La Concordia","Miravalle","Panorama","Residencial Guadalupe"],"coords":{"lat":21.8891983,"lon":-102.3158417}},"20049":{"cp":"20049","estado":"Aguascalientes","municipio":"Aguascalientes","colonias":["Colinas del Poniente"],"coords":{"lat":21.89302826,"lon":-102.3235474}},"20050":{"cp":"20050","estado":"Aguascalientes","municipio":"Aguascalientes","colonias":["Bugambilias","Del Carmen","La Fe","Primavera","San Pablo"],"coords":{"lat":21.88920403,"lon":-102.3023987}},"20059":{"cp":"20059","estado":"Aguascalientes","municipio":"Aguascalientes","colonias":["Guadalupe","Heliodoro García"],"coords":{"lat":21.8857975,"lon":-102.3038406}},"20060":{"cp":"20060","estado":"Aguascalientes","municipio":"Aguascalientes","colonias":["Gómez","Moderno"],"coords":{"lat":21.8832531,"lon":-102.315773}},"20064":{"cp":"20064","estado":"Aguascalientes","municipio":"Aguascalientes","colonias":["Valle del Rio San Pedro"],"coords":{"lat":21.88311005,"lon":-102.3210297}},"20070":{"cp":"20070","estado":"Aguascalientes","municipio":"Aguascalientes","colonias":["Guadalupe Posada","San Marcos","San Marcos"],"coords":{"lat":21.88366699,"lon":-102.3114929}},"20078":{"cp":"20078","estado":"Aguascalientes","municipio":"Aguascalientes","colonias":["San Marcos"],"coords":{"lat":21.87921906,"lon":-102.3209457}},"20080":{"cp":"20080","estado":"Aguascalientes","municipio":"Aguascalientes","colonias":["Modelo","Residencial del Valle I"],"coords":{"lat":21.87682533,"lon":-102.3095245}},"20089":{"cp":"20089","estado":"Aguascalientes","municipio":"Aguascalientes","colonias":["Residencial del Valle II"],"coords":{"lat":21.87462616,"lon":-102.3210373}}}