{"20800":{"cp":"20800","estado":"Aguascalientes","municipio":"Calvillo","colonias":["Calvillo Centro"]},"20802":{"cp":"20802","estado":"Aguascalientes","municipio":"Calvillo","colonias":["Unión Antorchista","El Mirador","Independencia","López Mateos","Las Paseras","Vista Hermosa","Campo Militar 14 CINE","El Guayabo","Benito Juárez","Los Cerritos","Loma de Fundadores"]},"20803":{"cp":"20803","estado":"Aguascalientes","municipio":"Calvillo","colonias":["Benito Juárez","Lomas de Huejúcar","San Nicolás","El Llano (El Llano de San Rafael)","San Rafael","Rincón de Baltazares","José Landeros"]},"20804":{"cp":"20804","estado":"Aguascalientes","municipio":"Calvillo","colonias":["Ejidal","Liberal","Rincón de Baltazares","Valle de Santiago","Arroyo de Los Caballos","Del Carmen","Azteca","Morelos"]},"20805":{"cp":"20805","estado":"Aguascalientes","municipio":"Calvillo","colonias":["Cerrito Alto","Ejido Calvillo (Sector Emiliano Zapata)","Emiliano Zapata","Las Flores","Martínez","Valle de Huejúcar","Los Ángeles","Chicago"]},"20810":{"cp":"20810","estado":"Aguascalientes","municipio":"Calvillo","colonias":["El Terrero de la Labor","Palo Alto","Junta de los Ríos"]},"20816":{"cp":"20816","estado":"Aguascalientes","municipio":"Calvillo","colonias":["El Sauz de la Labor","El Zapote de la Labor","Las Cuevas de la Labor","Las Rubias","Piedras Chinas","El Jagüey","Los Lazos","Puerta de Fragua (Presa la Codorniz)"]},"20820":{"cp":"20820","estado":"Aguascalientes","municipio":"Calvillo","colonias":["La Pochota","El Mirador","San Tadeo","El Potrerito","La Teresa","Mezquitillos","La Primavera","Jardines de San Isidro (Colonia Limón)","Solidaridad"]},"20823":{"cp":"20823","estado":"Aguascalientes","municipio":"Calvillo","colonias":["Los Arellano","Presa Ordeña Vieja","El Tepozán"]},"20830":{"cp":"20830","estado":"Aguascalientes","municipio":"Calvillo","colonias":["Chiquihuitero (San Isidro)","La Panadera","Las Víboras (Viborillas)","Villas del Laurel"]},"20832":{"cp":"20832","estado":"Aguascalientes","municipio":"Calvillo","colonias":["El Maguey","El Sauz","La Joya"]},"20834":{"cp":"20834","estado":"Aguascalientes","municipio":"Calvillo","colonias":["Potrero de los López","Las Huertas","La Pila","La Alberca","La Españita","Los Baños","Los Esparza","La Placita","La Casa Grande","Azoteyita","Bajío de Colomos","El Llano de López","El Morancillo (Los Arcos)","Colomos","Catana","El Cuervero (Cuerveros)","Malpaso","Ojocaliente","Potrero de los López","Tepezalilla de Abajo","La Fragua","El Jaralito","La Fortuna","Los Arcos","Magisterial"]},"20835":{"cp":"20835","estado":"Aguascalientes","municipio":"Calvillo","colonias":["Río Gil","Río Gil de Arriba"]},"20836":{"cp":"20836","estado":"Aguascalientes","municipio":"Calvillo","colonias":["Guajolotes (Huijolotes)","Los Muñoz","El Capulín","Montoro","Mesa de los Pozos (La Laguna)"]},"20840":{"cp":"20840","estado":"Aguascalientes","municipio":"Calvillo","colonias":["Los Mirasoles"]},"20842":{"cp":"20842","estado":"Aguascalientes","municipio":"Calvillo","colonias":["Las Joyas","San José de los Laureles"]},"20844":{"cp":"20844","estado":"Aguascalientes","municipio":"Calvillo","colonias":["Chimaltitán"]},"20850":{"cp":"20850","estado":"Aguascalientes","municipio":"Calvillo","colonias":["Crucero las Pilas","Las Moras","Mesa Grande","El Refugio (Las Praderas)","Pozo de los Artistas"]},"20852":{"cp":"20852","estado":"Aguascalientes","municipio":"Calvillo","colonias":["Ejido Calvillo (El Polvorín Sector Benito Juárez)","Los Adobes","Arroyo Ojocalientillo"]},"20854":{"cp":"20854","estado":"Aguascalientes","municipio":"Calvillo","colonias":["Parque Industrial Calvillo","El Tepetate de Arriba","La Calixtina","El Tepetate de Abajo","Ojo de Agua","Barranca del Roble","El Taray"]},"20855":{"cp":"20855","estado":"Aguascalientes","municipio":"Calvillo","colonias":["Los Alisos","El Garruño"]},"20856":{"cp":"20856","estado":"Aguascalientes","municipio":"Calvillo","colonias":["El Güencho","Jaltiche de Arriba","Mesa del Roble"]},"20860":{"cp":"20860","estado":"Aguascalientes","municipio":"Calvillo","colonias":["Cerro Blanco","El Salitre","Las Ánimas","Las Pilas","Michoacanejo","El Tepalcate"]},"20862":{"cp":"20862","estado":"Aguascalientes","municipio":"Calvillo","colonias":["Norias Cuatas","Salitrillo","Jaltiche de Abajo","La Media Luna","La Rinconada","Las Tinajas"]},"20864":{"cp":"20864","estado":"Aguascalientes","municipio":"Calvillo","colonias":["El Caracol","El Terrero del Refugio","Presa de los Serna"]},"20870":{"cp":"20870","estado":"Aguascalientes","municipio":"Calvillo","colonias":["Arboledas de Calvillo","El Papantón","El Rodeo","Los Patos","San José","Santos","Vaquerías","Barranca de Portales"]},"20872":{"cp":"20872","estado":"Aguascalientes","municipio":"Calvillo","colonias":["Peña Blanca","El Tigre","Miguel Hidalgo (El Huarache)","Presa de los Bajíos"]},"20874":{"cp":"20874","estado":"Aguascalientes","municipio":"Calvillo","colonias":["El Ocote [Banco de Tierra]","Las Trojes","Tanque de los Serna","La Ciénega"]},"20880":{"cp":"20880","estado":"Aguascalientes","municipio":"Calvillo","colonias":["La Labor","Temazcal","Paredes","La Hiedra","Ventanillas","El Salitrillo"]},"20882":{"cp":"20882","estado":"Aguascalientes","municipio":"Calvillo","colonias":["Manguillas"]}}