{"21900":{"cp":"21900","estado":"Baja California","municipio":"Mexicali","colonias":["Jiquilpan","Benito Juárez (Ejido Tecolotes)","México","Piedras Negras","Familia Soto Arriola (Colonia Tecolote Batáquez)"]},"21902":{"cp":"21902","estado":"Baja California","municipio":"Mexicali","colonias":["General Álvaro Obregón (Tierras Blancas)"]},"21904":{"cp":"21904","estado":"Baja California","municipio":"Mexicali","colonias":["Tehuantepec (Santa Rosa)"]},"21905":{"cp":"21905","estado":"Baja California","municipio":"Mexicali","colonias":["Tabasco","El Chorizo"]},"21910":{"cp":"21910","estado":"Baja California","municipio":"Mexicali","colonias":["Netzahualcóyotl","Irapuato","Lázaro Cárdenas (La Mosca)","Bórquez Norte (La Canaleta)","Yucatán","Tayjón (Ejido Yucatán)","Las Cumbres","Agro Altima"]},"21911":{"cp":"21911","estado":"Baja California","municipio":"Mexicali","colonias":["Tamaulipas (Estación Cucapah)","Tula","Familia Machado"]},"21913":{"cp":"21913","estado":"Baja California","municipio":"Mexicali","colonias":["Represa Aurelio Benansini (Carehey)","Monterrey (Colonia Batáquez)"]},"21920":{"cp":"21920","estado":"Baja California","municipio":"Mexicali","colonias":["Pérez (Ejido Yucatán)","Mérida","Paredones","Ciudad Victoria"]},"21921":{"cp":"21921","estado":"Baja California","municipio":"Mexicali","colonias":["Villa Hermosa","El Tres (Villa Hermosa)","Familia Mascareño"]},"21925":{"cp":"21925","estado":"Baja California","municipio":"Mexicali","colonias":["Mesa Arenosa de Andrade (Villa Zapata)"]},"21930":{"cp":"21930","estado":"Baja California","municipio":"Mexicali","colonias":["Tecolote Batáquez","Miguel Alemán","Puente Treviño"]},"21950":{"cp":"21950","estado":"Baja California","municipio":"Mexicali","colonias":["Janitzio","Guadalajara"]},"21951":{"cp":"21951","estado":"Baja California","municipio":"Mexicali","colonias":["Janitzio 2","La 27 (Campamento SARH Km. 27)"]},"21960":{"cp":"21960","estado":"Baja California","municipio":"Mexicali","colonias":["Ciudad Morelos (Cuervos)","27 de Enero"]},"21961":{"cp":"21961","estado":"Baja California","municipio":"Mexicali","colonias":["Tepic","Campo Diecinueve (Ej. Morelos Colonia el Suspiro)","La Quince (Tepic)"]},"21963":{"cp":"21963","estado":"Baja California","municipio":"Mexicali","colonias":["José María Rodríguez Mérida (La Panga)","Esquer (Orive de Alba)","Cuervitos","Orive de Alba (Sume)"]},"21964":{"cp":"21964","estado":"Baja California","municipio":"Mexicali","colonias":["Leyes de Reforma","Puente Calabazas (Represa Galeana)","Granados (Recursos Hidráulicos)"]},"21965":{"cp":"21965","estado":"Baja California","municipio":"Mexicali","colonias":["Campo el Dieciocho (Morelos)"]},"21966":{"cp":"21966","estado":"Baja California","municipio":"Mexicali","colonias":["Canal Álamo"]},"21970":{"cp":"21970","estado":"Baja California","municipio":"Mexicali","colonias":["Del Valle","República Mexicana","Dieguinos","Ladrillera","Vicente Guerrero (Algodones)","Francisco Santana Peralta","Residencial Valle Santa Fe","General J. Gertrudis García Sánchez"]},"21980":{"cp":"21980","estado":"Baja California","municipio":"Mexicali","colonias":["5 de Mayo","Pachuca","Bordo Okerson (Represa Galeana)"]}}