{"41900":{"cp":"41900","estado":"Guerrero","municipio":"Azoyú","colonias":["Matacuba","El Tepeyac","San José","Azoyu Centro","Del Panteón","Las Ollitas","Oriente","Poniente","Tixnapa","Del Zorro"]},"41905":{"cp":"41905","estado":"Guerrero","municipio":"Azoyú","colonias":["Arcelia del Progreso","Zapotitlán de La Fuente (El Zapote)","Peñas Negras"]},"41906":{"cp":"41906","estado":"Guerrero","municipio":"Azoyú","colonias":["Maxmandi","Rancho el Mesón","Rancho Carlota Viuda de Peña","Rancho Cerro Cuate","Rancho Mario Bautista","Agua Fría","El Potrero","El Salto","El Tamarindo","La Culebra","Las Pilitas","Tencohuey"]},"41907":{"cp":"41907","estado":"Guerrero","municipio":"Azoyú","colonias":["Quetzalapa"]},"41910":{"cp":"41910","estado":"Guerrero","municipio":"Azoyú","colonias":["El Carrizo","La Pelota","San Isidro el Puente (El Puente)","Rancho la Antena","Rancho el Centenario (Rancho Luis Justo)","Rancho Bautista Dos (Hermanos B. Florentino)","Rancho Dos Potrillos (Rancho Luis Justo H.)","Rancho Ángel Zurita","Rancho Dos Laureles","Rancho Eleazar Zurita","Rancho Muñoz Castellanos","Finca los Pumas (Crucero Lomas del Vidal)","La Mazacuata","Llano del Muerto (Rancho de Chema Rodríguez)","Lomas del Vidal (El Vidal)"]},"41913":{"cp":"41913","estado":"Guerrero","municipio":"Azoyú","colonias":["El Macahuite","Rancho Magdaleno Justo","Rancho Hermenegildo Antonio Hernández","Rancho Edrey Bautista","Rancho Hermanos Alvarado (Crucero de Huehuetán)","Rancho Lauro Justo (Amate Guinea)","Toxnene"]},"41914":{"cp":"41914","estado":"Guerrero","municipio":"Azoyú","colonias":["Tenango","Talapilla","Rancho Muñoz","Rancho Gabriel Herrera","Rancho Lempira","Rancho Celso Muñoz","Aguacatillo (Rancho Maximino Muñoz)","El Mango"]},"41915":{"cp":"41915","estado":"Guerrero","municipio":"Azoyú","colonias":["Chalacatepec","Cola de Charco (Charco Grande)","La Bocana","Las Trancas","Los Chegües","Palo Blanco","Playa Suave","Rosendo Balanzar García [Rancho]","Tres Pelos","Zapotitán"]},"41916":{"cp":"41916","estado":"Guerrero","municipio":"Azoyú","colonias":["Huehuetán","Rancho Herrera Martínez","Rancho el Charro (Celso Alvarado Nolasco)","Charco de Alfonso Cruz (Los Carmona la Loma)","Escuela Secundaria J. García J. (Crucero de Huehuetán)","La Amatera","Los Metates","Los Quiterios"]},"41917":{"cp":"41917","estado":"Guerrero","municipio":"Azoyú","colonias":["Banco de Oro","El Arenal (La Plataforma)","Rancho Mario Navarrete","Adalberto Sáligan Ávila (Playa Larga)","Rancho Manzanárez Cortez","Rancho Isabel Rodríguez","Rancho Hermanos Cortez","Rancho Maximiliano Mendoza (Rancho de Lango)","Rancho Carlos Villanueva Mendoza","Rancho los Mendoza","Rancho Mariana Cortez","Charco Choco (Rancho Domingo Martínez)","La Unión de los Hernández","Rancho Paulino Dámaso Mayo","Villa de Cortez"]},"41920":{"cp":"41920","estado":"Guerrero","municipio":"Juchitán","colonias":["Juchitán"]},"41922":{"cp":"41922","estado":"Guerrero","municipio":"Juchitán","colonias":["El Naranjo"]},"41923":{"cp":"41923","estado":"Guerrero","municipio":"Juchitán","colonias":["Vista Hermosa"]},"41924":{"cp":"41924","estado":"Guerrero","municipio":"Juchitán","colonias":["Rancho Salvador Galindo ((Las Penas)","Rancho Camilo Carmona"]},"41926":{"cp":"41926","estado":"Guerrero","municipio":"Juchitán","colonias":["Los Callejones","Rayito de Luna","Rancho el Tarillal (Juan Alarcón Soriano)","Rancho Urbano Jiménez","Rancho Cisneros"]},"41927":{"cp":"41927","estado":"Guerrero","municipio":"Juchitán","colonias":["Carrizalillo","Barrio Nuevo","San José del Capulín"]},"41928":{"cp":"41928","estado":"Guerrero","municipio":"Juchitán","colonias":["Los Pelillos","Plan de Buena Vista","La Cuchilla","Agua Zarca","El Aguacate","El Coco"]},"41930":{"cp":"41930","estado":"Guerrero","municipio":"Marquelia","colonias":["El Panteón","El Zapote","Nuevo Marquelia","Marquelia Centro","18 de Octubre","16 de Septiembre","El Polvorín","La Noria","Progreso","ISSSTE","Carrillo","Plan de Ayala","Miramar"]},"41933":{"cp":"41933","estado":"Guerrero","municipio":"Marquelia","colonias":["La Finca O El Palmar","Tepantitlán"]},"41934":{"cp":"41934","estado":"Guerrero","municipio":"Marquelia","colonias":["Zoyatlán","El Capulín Chocolate","Cruz Verde"]},"41936":{"cp":"41936","estado":"Guerrero","municipio":"Marquelia","colonias":["La Ceniza (Loma de Romero)","Barranca de Tecoanapa","La Guadalupe"]},"41937":{"cp":"41937","estado":"Guerrero","municipio":"Marquelia","colonias":["La Bocana"]},"41940":{"cp":"41940","estado":"Guerrero","municipio":"Cuajinicuilapa","colonias":["Cuajicuinalpa Centro"]},"41943":{"cp":"41943","estado":"Guerrero","municipio":"Cuajinicuilapa","colonias":["Lomas del Carmen"]},"41944":{"cp":"41944","estado":"Guerrero","municipio":"Cuajinicuilapa","colonias":["San Judas Tadeo","2 de Diciembre"]},"41945":{"cp":"41945","estado":"Guerrero","municipio":"Cuajinicuilapa","colonias":["Vicente Guerrero"]},"41946":{"cp":"41946","estado":"Guerrero","municipio":"Cuajinicuilapa","colonias":["Chuparrosa","La Guadalupe","Los Lirios","Las Parotas","Campo Deportivo"]},"41947":{"cp":"41947","estado":"Guerrero","municipio":"Cuajinicuilapa","colonias":["Doctores","La Banda"]},"41948":{"cp":"41948","estado":"Guerrero","municipio":"Cuajinicuilapa","colonias":["Del Panteón"]},"41949":{"cp":"41949","estado":"Guerrero","municipio":"Cuajinicuilapa","colonias":["San Francisco","La Gloria"]},"41950":{"cp":"41950","estado":"Guerrero","municipio":"Cuajinicuilapa","colonias":["Comaltepec (Comal)","El Terrero","El Cuiji (El Cuije)"]},"41951":{"cp":"41951","estado":"Guerrero","municipio":"Cuajinicuilapa","colonias":["Barajillas (Barajilla)","Miguel Alemán Valdez"]},"41952":{"cp":"41952","estado":"Guerrero","municipio":"Cuajinicuilapa","colonias":["Cerro de las Tablas"]},"41954":{"cp":"41954","estado":"Guerrero","municipio":"Cuajinicuilapa","colonias":["Cerro del Indio (El Indio)"]},"41955":{"cp":"41955","estado":"Guerrero","municipio":"Cuajinicuilapa","colonias":["El Quizá","De Santiago (Rancho Santiago)"]},"41956":{"cp":"41956","estado":"Guerrero","municipio":"Cuajinicuilapa","colonias":["Montecillos"]},"41957":{"cp":"41957","estado":"Guerrero","municipio":"Cuajinicuilapa","colonias":["Buenos Aires","El Vaivén","Maldonado"]},"41958":{"cp":"41958","estado":"Guerrero","municipio":"Cuajinicuilapa","colonias":["San José","Tierra Colorada"]},"41960":{"cp":"41960","estado":"Guerrero","municipio":"San Nicolás","colonias":["San Nicolás"]},"41964":{"cp":"41964","estado":"Guerrero","municipio":"San Nicolás","colonias":["El Cacalote"]},"41965":{"cp":"41965","estado":"Guerrero","municipio":"San Nicolás","colonias":["El Tamale","El Jícaro"]},"41966":{"cp":"41966","estado":"Guerrero","municipio":"San Nicolás","colonias":["El Pitahayo","Hacienda la Petaca"]},"41968":{"cp":"41968","estado":"Guerrero","municipio":"San Nicolás","colonias":["Punta Maldonado","Tejas Crudas"]},"41970":{"cp":"41970","estado":"Guerrero","municipio":"Igualapa","colonias":["Igualapa","Yoloxóchitl","Del Tepeyac","La Playa","Alejandro Cervantes Delgado","La Gachupina","Los Tepetates","Del Camposanto","Nuevo","PRI 2000"]},"41980":{"cp":"41980","estado":"Guerrero","municipio":"Igualapa","colonias":["Llano Grande de Juárez","San José Buenavista","Rancho el Arbolito (Juan Cristóbal)"]},"41985":{"cp":"41985","estado":"Guerrero","municipio":"Igualapa","colonias":["Acalmani"]},"41987":{"cp":"41987","estado":"Guerrero","municipio":"Igualapa","colonias":["Chacalapa"]},"41993":{"cp":"41993","estado":"Guerrero","municipio":"Igualapa","colonias":["La Victoria","Llano Grande de los Hilarios"]},"41994":{"cp":"41994","estado":"Guerrero","municipio":"Igualapa","colonias":["La Libertad"]},"41995":{"cp":"41995","estado":"Guerrero","municipio":"Igualapa","colonias":["Tepatahuac"]},"41996":{"cp":"41996","estado":"Guerrero","municipio":"Igualapa","colonias":["El Capulín","Enrique Rodríguez Cruz"]},"41997":{"cp":"41997","estado":"Guerrero","municipio":"Igualapa","colonias":["San Juan de los Llanos","Boca de Talapa","El Barrero"]},"41998":{"cp":"41998","estado":"Guerrero","municipio":"Igualapa","colonias":["La Reforma"]}}