{"45100":{"cp":"45100","estado":"Jalisco","municipio":"Zapopan","colonias":["La Villa","Zapopan Centro"]},"45110":{"cp":"45110","estado":"Jalisco","municipio":"Zapopan","colonias":["Villa la Cima","El Alcazar Poniente","El Alcazar Oriente","Colinas de San Javier","Jacarandas","Jardines de La Patria","Jardines Universidad","Real San Bernardo","Santa Isabel","San Bernardo","San Wenceslao","Vallarta Universidad","Villa Universitaria","Virreyes Residencial","Colomos Patria"]},"45115":{"cp":"45115","estado":"Jalisco","municipio":"Zapopan","colonias":["Puerta las Lomas","Colinas Virreyes","Entrelomas Residencial","Residencial Parque Virreyes","Villa Verona","Los Castaños","Vistas del Tule I","Vistas del Tule II"]},"45116":{"cp":"45116","estado":"Jalisco","municipio":"Zapopan","colonias":["Puerta Aqua","Puerta del Bosque","Real del Parque","Puerta de Hierro","Royal Country","Puerta Plata","Puerta Del Roble","Pontevedra"]},"45117":{"cp":"45117","estado":"Jalisco","municipio":"Zapopan","colonias":["Vista Magna","La Laja","Parque de La Castellana","Parque Regency","El Rincón","Puerta del Sol","Callejón del Parque"]},"45118":{"cp":"45118","estado":"Jalisco","municipio":"Zapopan","colonias":["Atlas Colomos","El Prado","Guadalajarita","Lomas de las Palmas","Lomas Del Bosque","Zotogrande"]},"45119":{"cp":"45119","estado":"Jalisco","municipio":"Zapopan","colonias":["La Patria Universidad"]},"45120":{"cp":"45120","estado":"Jalisco","municipio":"Zapopan","colonias":["Juan Manuel Vallarta","Los Pinos","Unidad México","Vigusa","Hacienda de Las Lomas","Villas de San Javier","Rinconada Santa Rita"]},"45128":{"cp":"45128","estado":"Jalisco","municipio":"Zapopan","colonias":["La Favorita","Lomas Altas"]},"45129":{"cp":"45129","estado":"Jalisco","municipio":"Zapopan","colonias":["Loma Real","Lomas Del Valle","Los Palomos"]},"45130":{"cp":"45130","estado":"Jalisco","municipio":"Zapopan","colonias":["Arándanos Cañada Residencial","Altagracia","Arcos de Zapopan 1a. Sección","Arcos de Zapopan 2a. Sección","Lomas de Zapopan","San Francisco","Zapopan Industrial Norte","Colinas Del Rey","Francisco Villa","Mirador de San Isidro","Rinconadas de las Palmas","Villas de Torremolinos","Real del Bosque","Casa Grande","Real de Valdepeñas","Real del Camichin","Bosques de Zapopan","Bosque Valdepeñas","Hacienda del Sol","Punta Valdepeñas 2","Punta Valdepeñas 1","Cañadas de San Lorenzo"]},"45133":{"cp":"45133","estado":"Jalisco","municipio":"Zapopan","colonias":["Altavista Residencial","Praderas del Centinela","Canteras del Centinela","Zoi Cañadas","Real de Valdepeñas II","Vitana Residencial","Montes","Vista Sur Residencial","Argenta Mirador Residencial","Punta Centinela","Magnolia","La Vista","Colinas de San Isidro","Sotavento","Residencial Los Cedros","Cipreses","Los Fresnos","Los Robles","Sauces","Los Abetos","Olmos","Nogales","Encinos","Savia Tulipan","Savia Orquidea","Jacarandas","Savia Jazmín","Residencial Ave del Paraíso","Los Sabinos","Los Álamos","Altika","El Acantilado","Las Cañadas (Bosques de San Isidro)","San Isidro","Colinas Del Centinela","Mirador de San Isidro","Haciendas Del Valle","Villas Del Mirador","Valle de San Isidro","Haciendas Del Valle 2a Sección","Misión Del Bosque","Parques Del Centinela","Residencial San Isidro","Mirador de La Cañada","Rancho El Centinela","Misión de San Isidro","Los Almendros"]},"45134":{"cp":"45134","estado":"Jalisco","municipio":"Zapopan","colonias":["La Moraleja","Real Cantabria","Campestre Los Robles","Los Guayabos","Madeiras","Puerta Serena","La Sauceda","Sendas Residencial","Altaterra","Altaterra II","Los Nísperos","Canteras","Colinas de San Miguel","Alva Residencial","Abie","Nara","Creta Residencial","Carrara","Capital Norte","Colina de los Robles","El Tigre","El Zapote","Los Robles","Valles de Nuevo México (La Periquera)","Vicente Guerrero","Rio Blanco","Lomas de San Gonzalo","Coto Miraflores","Marcelino García Barragán","Villas La Loma","Villas del Valle","Los Alamitos","Bosques de San Gonzalo","Jardines de San Gonzalo","Bosque de Los Encinos","Campo Real","Placita del Sol","Colinas del Río Blanco","La Cima","Valle Imperial"]},"45136":{"cp":"45136","estado":"Jalisco","municipio":"Zapopan","colonias":["La Toscana","Novaterra","Real del Carmen","Residencial del Valle","Real del Carmen Grand","La Ceiba","Lugano","Abadía","La Mora","Los Girasoles","Residencial Poniente","Jardín Real","Parque Real","Las Lomas Club Golf","Puerta Real","Puerta del Valle","Rinconadas del Valle"]},"45138":{"cp":"45138","estado":"Jalisco","municipio":"Zapopan","colonias":["Rinconadas de Zapopan","Rinconada del Aire","Los Mandarinos","Jardines San Francisco","Armonía Hábitat","Puerta Laurel","Lucero del Valle","Pacífica Habitat","El Real","El Secreto","Carrara Residencial","Villas del Aire","Las Bóvedas","Flores del Valle","La Tuzania","Ex Hacienda de La Mora","Jardines Del Valle","La Casita","Girasoles Elite","Jardines de Nuevo México","V Región Militar","Nuevo México","Hogares de Nuevo México","Parques de Zapopan","Héroes Nacionales","Jardines de Santa Margarita","Base Aérea Militar No. 5","Misión del Valle","Praderas de San Antonio","Colegio Del Aire","Luis Donaldo Colosio","Girasoles Acueducto","Misión Jardines","Villas de Nuevo México","Misión del Valle II","Residencial Santa Fe","El Olivo","La Noria Residencial","Valle Esmeralda","El Fresno","Santa Margarita Residencial","Rinconada de Los Fresnos","El Triángulo","Viveros del Valle"]},"45140":{"cp":"45140","estado":"Jalisco","municipio":"Zapopan","colonias":["U.A.G.","El Vigía","La Loma","San Francisco","San José del Bajío","Santa Margarita","Unidad Abastos Belenes","Residencial los Frailes"]},"45145":{"cp":"45145","estado":"Jalisco","municipio":"Zapopan","colonias":["Parque Industrial Belenes Norte"]},"45146":{"cp":"45146","estado":"Jalisco","municipio":"Zapopan","colonias":["Unidad República"]},"45147":{"cp":"45147","estado":"Jalisco","municipio":"Zapopan","colonias":["San Isidro Ejidal"]},"45148":{"cp":"45148","estado":"Jalisco","municipio":"Zapopan","colonias":["La Arboleda"]},"45149":{"cp":"45149","estado":"Jalisco","municipio":"Zapopan","colonias":["Unidad FOVISSSTE"]},"45150":{"cp":"45150","estado":"Jalisco","municipio":"Zapopan","colonias":["El Capullo","La Hoja Verde","Los Maestros","San Miguel de La Cañada","Seattle","Tepeyac","Ecológica Seattle"]},"45157":{"cp":"45157","estado":"Jalisco","municipio":"Zapopan","colonias":["Los Paraísos","Industrial los Belenes","Villa de los Belenes","Rinconada López Cotilla","El Paraíso"]},"45158":{"cp":"45158","estado":"Jalisco","municipio":"Zapopan","colonias":["Los Laureles","San Gilberto","Prados de San Ignacio","Los Abetos","Conjunto Zapopan","Rinconada de las Azaleas","Aves del Paraíso"]},"45159":{"cp":"45159","estado":"Jalisco","municipio":"Zapopan","colonias":["La Aurora"]},"45160":{"cp":"45160","estado":"Jalisco","municipio":"Zapopan","colonias":["Agraria","Altamira","Residencial Patria","Jacarandas","Patria","Patria Raquet","Patria Zoquipan","San Miguel de la Colina","Villa San Jorge","Plaza Patria","Villas del Bosque"]},"45167":{"cp":"45167","estado":"Jalisco","municipio":"Zapopan","colonias":["Loma Blanca"]},"45168":{"cp":"45168","estado":"Jalisco","municipio":"Zapopan","colonias":["Santa Fe"]},"45169":{"cp":"45169","estado":"Jalisco","municipio":"Zapopan","colonias":["Lindavista","Villa Coral","Villa Magna","Villa Palmas"]},"45170":{"cp":"45170","estado":"Jalisco","municipio":"Zapopan","colonias":["Colinas de Atemajac","Conjunto Seattle","GVSA","Zoquipan","Ejido de Zoquiapan"]},"45176":{"cp":"45176","estado":"Jalisco","municipio":"Zapopan","colonias":["Unidad Patria","Lomas del Camino"]},"45177":{"cp":"45177","estado":"Jalisco","municipio":"Zapopan","colonias":["Lagos del Country"]},"45178":{"cp":"45178","estado":"Jalisco","municipio":"Zapopan","colonias":["Lomas de Atemajac"]},"45179":{"cp":"45179","estado":"Jalisco","municipio":"Zapopan","colonias":["Santa Paula"]},"45180":{"cp":"45180","estado":"Jalisco","municipio":"Zapopan","colonias":["Jardines Seattle Unidad","Las Fuentes","Constitución","Jardines de La Esperanza","José López Portillo","La Huerta","Los Cerritos","Nuevo Vergel","Parques del Auditorio","Unidad Auditorio 1a. Secc.","Unidad Auditorio 2a Secc","CUCEA Universidad de Guadalajara","27 de Septiembre","Venustiano Carranza","Villas Del Marques","Pedro Moreno","La Palmita","División del Norte","Jardines Del Auditorio","Del Federalismo","Rinconada San Isidro","La Joya","La Grana","Hacienda San Joaquín","Jardines Del Vergel","Rinconada Auditorio","Bosque Escondido","Quinta Del Federalismo","Hogar de Atemajac","Jardines del Porvenir","Las Cabañitas","Jardines de la Cantera","Colinas de los Belenes"]},"45184":{"cp":"45184","estado":"Jalisco","municipio":"Zapopan","colonias":["Constituyentes","Hermenegildo Galeana"]},"45185":{"cp":"45185","estado":"Jalisco","municipio":"Zapopan","colonias":["Colinas de Tabachines","Lomas de Tabachines","La Martinica","Emiliano Zapata","Alamedas de Tesistán"]},"45186":{"cp":"45186","estado":"Jalisco","municipio":"Zapopan","colonias":["Agua Fría","Arroyo Hondo","Balcones de La Cantera","Miguel Hidalgo","Arroyo Hondo 2a Secc","Lomas Del Refugio","Nueva España"]},"45187":{"cp":"45187","estado":"Jalisco","municipio":"Zapopan","colonias":["Alba","Bosques del Centinela","Villas Del Centinela","Lomas Del Centinela","Rinconada de Los Sauces","Quintas del Bosque","El Bosque"]},"45188":{"cp":"45188","estado":"Jalisco","municipio":"Zapopan","colonias":["Jardines de Tabachines","Lomas Del Vergel","Tabachines","San Nicolás de los Belenes","Rinconadas Tabachines","Residencial Tabachines"]},"45189":{"cp":"45189","estado":"Jalisco","municipio":"Zapopan","colonias":["Villas de Guadalupe","Vista Hermosa","Crucero de La Mesa","Mesa Colorada Oriente","Mesa Colorada Poniente","Mesa de los Ocotes","La Coronilla","Pedregal Zapopan","La Higuera","Coronilla Del Ocote","Mirador Escondido"]},"45190":{"cp":"45190","estado":"Jalisco","municipio":"Zapopan","colonias":["Atemajac Del Valle","El Batan","González Ortega","Hogares","Indígena de Mezquitán","Jardines de los Belenes","Las Palomas","Lomas Del Batan","Los Canteros","Conjunto Ritz","Victor Hugo","Villa Atemajac","Villas Alcalde","Azaleas Del Valle","El Carrizal"]},"45198":{"cp":"45198","estado":"Jalisco","municipio":"Zapopan","colonias":["La Experiencia","Molino Del Salvador"]},"45199":{"cp":"45199","estado":"Jalisco","municipio":"Zapopan","colonias":["Benito Juárez","Benito Juárez Norte"]}}