{"54300":{"cp":"54300","estado":"México","municipio":"Villa del Carbón","colonias":["Villa del Carbón"]},"54310":{"cp":"54310","estado":"México","municipio":"Villa del Carbón","colonias":["San Jerónimo Zacapexco"]},"54313":{"cp":"54313","estado":"México","municipio":"Villa del Carbón","colonias":["La Capilla","Palo Hueco (Kilómetro 5)","Loma de la Hacienda","Bocanegra","Los Domínguez"]},"54314":{"cp":"54314","estado":"México","municipio":"Villa del Carbón","colonias":["Magisterial","Los Gutiérrez","La Bellota","Club Campestre Villa del Actor"]},"54315":{"cp":"54315","estado":"México","municipio":"Villa del Carbón","colonias":["Monte de Peña","El Plan Villa"]},"54320":{"cp":"54320","estado":"México","municipio":"Villa del Carbón","colonias":["La Cañada","San Salvador de la Laguna","La Arrastradera"]},"54324":{"cp":"54324","estado":"México","municipio":"Villa del Carbón","colonias":["La Cruz y Carrizal","Loma Alta Taxhimay","El Arenal","El Palomar"]},"54325":{"cp":"54325","estado":"México","municipio":"Villa del Carbón","colonias":["Golondrinas","San Luis Taxhimay"]},"54326":{"cp":"54326","estado":"México","municipio":"Villa del Carbón","colonias":["San Luis Anáhuac (Toriles)","Las Moras","Los Oratorios","Xajay (Loma del Xajay)","La Escalera","Potrero Largo (Villa del Potrero)"]},"54327":{"cp":"54327","estado":"México","municipio":"Villa del Carbón","colonias":["Santa Catarina","Los Madroños","Villa del Carbón"]},"54330":{"cp":"54330","estado":"México","municipio":"Villa del Carbón","colonias":["El Ocotal","Llano de Zacapexco","San Lucas"]},"54333":{"cp":"54333","estado":"México","municipio":"Villa del Carbón","colonias":["Loma Alta","San Martín Cachihuapan","Loma de Don Juan","Loma de Trojes","Los Platitos (Colonia los Platitos)","La Ciénega"]},"54334":{"cp":"54334","estado":"México","municipio":"Villa del Carbón","colonias":["El Varal","La Cruz del Arenal","La Centinela","Molinitos (Comunidad de los Molinitos)","Piequexhimo"]},"54335":{"cp":"54335","estado":"México","municipio":"Villa del Carbón","colonias":["Temanacoya (Barrio de Temanacoya)"]},"54336":{"cp":"54336","estado":"México","municipio":"Villa del Carbón","colonias":["Santa María"]},"54337":{"cp":"54337","estado":"México","municipio":"Villa del Carbón","colonias":["Los Barbechos","San Isidro del Bosque","Las Vigas","Los Rueda"]},"54340":{"cp":"54340","estado":"México","municipio":"Villa del Carbón","colonias":["Pueblo Nuevo"]},"54345":{"cp":"54345","estado":"México","municipio":"Villa del Carbón","colonias":["Los Arana"]},"54346":{"cp":"54346","estado":"México","municipio":"Villa del Carbón","colonias":["La Esperanza","El Cerrito","El Águila","Llano Grande"]},"54350":{"cp":"54350","estado":"México","municipio":"Chapa de Mota","colonias":["Chapa de Mota"]},"54360":{"cp":"54360","estado":"México","municipio":"Chapa de Mota","colonias":["Macavaca (Santa Ana Macavaca)","Barajas (Hacienda Vieja)","Ventey","El Chabacano"]},"54363":{"cp":"54363","estado":"México","municipio":"Chapa de Mota","colonias":["Barajas","Damate","La Soledad (El Mogote)"]},"54364":{"cp":"54364","estado":"México","municipio":"Chapa de Mota","colonias":["San José Ampabi","San Francisco de las Tablas","Las Ánimas"]},"54365":{"cp":"54365","estado":"México","municipio":"Chapa de Mota","colonias":["Xhoñe","Venú","La Loma"]},"54366":{"cp":"54366","estado":"México","municipio":"Chapa de Mota","colonias":["Mefi"]},"54367":{"cp":"54367","estado":"México","municipio":"Chapa de Mota","colonias":["Santa María","Xhote"]},"54373":{"cp":"54373","estado":"México","municipio":"Chapa de Mota","colonias":["Tenjay","Los Limones"]},"54374":{"cp":"54374","estado":"México","municipio":"Chapa de Mota","colonias":["La Palma","La Concepción"]},"54375":{"cp":"54375","estado":"México","municipio":"Chapa de Mota","colonias":["Cadenqui","El Salto","La Alameda (Las Lajas)"]},"54380":{"cp":"54380","estado":"México","municipio":"Chapa de Mota","colonias":["Dhalle (Ejido de Dongu)","Santa Elena","Danxho"]},"54383":{"cp":"54383","estado":"México","municipio":"Chapa de Mota","colonias":["La Ladera"]},"54384":{"cp":"54384","estado":"México","municipio":"Chapa de Mota","colonias":["La Esperanza"]},"54385":{"cp":"54385","estado":"México","municipio":"Chapa de Mota","colonias":["Dongu","San Felipe Coamango"]},"54386":{"cp":"54386","estado":"México","municipio":"Chapa de Mota","colonias":["San Juan Tuxtepec","San Gabriel","El Puerto"]},"54387":{"cp":"54387","estado":"México","municipio":"Chapa de Mota","colonias":["El Quinte","San Felipe Coamango"]}}