{"74300":{"cp":"74300","estado":"Puebla","municipio":"Nealtican","colonias":["Xaltepec","San Buenaventura Nealtican","Guadalupe Hidalgo"],"coords":{"lat":19.05426216,"lon":-98.42816162}},"74310":{"cp":"74310","estado":"Puebla","municipio":"San Jerónimo Tecuanipan","colonias":["Los Reyes Tlanechicolpan","San Miguel Papaxtla","San Jerónimo Tecuanipan"],"coords":{"lat":19.01660538,"lon":-98.40077209}},"74320":{"cp":"74320","estado":"Puebla","municipio":"San Gregorio Atzompa","colonias":["San Gregorio Atzompa"],"coords":{"lat":19.0207653,"lon":-98.34541321}},"74325":{"cp":"74325","estado":"Puebla","municipio":"San Gregorio Atzompa","colonias":["Chipilo de Francisco Javier Mina"],"coords":{"lat":19.00583649,"lon":-98.33123779}},"74330":{"cp":"74330","estado":"Puebla","municipio":"Tochimilco","colonias":["Jerusalén","San Lorenzo","Los Amates","La Concepción","La Magdalena Yancuitlalpan","Tochimilco"],"coords":{"lat":18.88776016,"lon":-98.56334686}},"74334":{"cp":"74334","estado":"Puebla","municipio":"Tochimilco","colonias":["Tepanapa"],"coords":{"lat":18.89337349,"lon":-98.6129837}},"74335":{"cp":"74335","estado":"Puebla","municipio":"Tochimilco","colonias":["Cuautomatitla","Tecuanipa","Zacatempa"],"coords":{"lat":18.87541771,"lon":-98.70513153}},"74336":{"cp":"74336","estado":"Puebla","municipio":"Tochimilco","colonias":["Cuilotepec"],"coords":{"lat":18.91039467,"lon":-98.61728668}},"74337":{"cp":"74337","estado":"Puebla","municipio":"Tochimilco","colonias":["Tochimizolco"],"coords":{"lat":18.86864471,"lon":-98.61087036}},"74339":{"cp":"74339","estado":"Puebla","municipio":"Tochimilco","colonias":["Alpanocan","Huilango","Tulcingo"],"coords":{"lat":18.84519577,"lon":-98.57953644}},"74340":{"cp":"74340","estado":"Puebla","municipio":"Tianguismanalco","colonias":["San Martín Tlapala","Tianguismanalco"],"coords":{"lat":18.96265411,"lon":-98.46155548}},"74342":{"cp":"74342","estado":"Puebla","municipio":"Tianguismanalco","colonias":["San Francisco Buenavista"],"coords":{"lat":18.93962479,"lon":-98.46559906}},"74343":{"cp":"74343","estado":"Puebla","municipio":"Tianguismanalco","colonias":["Santo Domingo Tenantitla","San Baltazar Atlimeyaya","San Pedro Atlixco"],"coords":{"lat":18.99153328,"lon":-98.48070526}},"74347":{"cp":"74347","estado":"Puebla","municipio":"Tianguismanalco","colonias":["Pueblos Mágicos"],"coords":null},"74348":{"cp":"74348","estado":"Puebla","municipio":"Tianguismanalco","colonias":["Villas el León","La Villa Tercera Sección","La Villa Segunda Sección","San Isidro Tlacxitla"],"coords":null},"74350":{"cp":"74350","estado":"Puebla","municipio":"Santa Isabel Cholula","colonias":["San Martín Tlamapa","Santa Isabel Cholula"],"coords":{"lat":18.99425316,"lon":-98.37865448}},"74355":{"cp":"74355","estado":"Puebla","municipio":"Santa Isabel Cholula","colonias":["San Pablo Ahuatempa"],"coords":{"lat":18.99707985,"lon":-98.38336182}},"74357":{"cp":"74357","estado":"Puebla","municipio":"Santa Isabel Cholula","colonias":["Tlamapa"],"coords":{"lat":18.95917892,"lon":-98.41033936}},"74358":{"cp":"74358","estado":"Puebla","municipio":"Santa Isabel Cholula","colonias":["Santa Ana Acozautla"],"coords":{"lat":18.92705917,"lon":-98.36747742}},"74360":{"cp":"74360","estado":"Puebla","municipio":"Atlixco","colonias":["Prados el León","Santa Elena Axocopan","Tenería","Ixtepec","Maravillas","Santa Cecilia","La Villa","Cabrera","El León","San Agustín Ixtahuixtla","Metepec","San Juan Tejaluca"],"coords":{"lat":18.92642784,"lon":-98.45457458}},"74363":{"cp":"74363","estado":"Puebla","municipio":"Atlixco","colonias":["Agrícola de Ocotepec (Colonia San José)","Guadalupe Huexocuapan","San Jerónimo Coyula","San Juan Ocotepec","San Miguel Ayala","San Pedro Benito Juárez"],"coords":{"lat":18.89079285,"lon":-98.52006531}},"74365":{"cp":"74365","estado":"Puebla","municipio":"Atlixco","colonias":["Solares de Tenextepec","San Juan de los Laureles","Mártir de Chinameca","Veracruz","La Vía","Moyotzingo","San Diego Acapulco","Axocopan","San Juan Castillotla","Chapultepec","La Sabana (San Juan la Sabana)","La Trinidad Tepango","Santa Cruz Axocopan","San Lorenzo los Jagüeyes","La Joya (Agropecuaria Tenextepec)","Lomas de Axocopan","Las Huertas de Jesús Primera Sección"],"coords":{"lat":18.86437416,"lon":-98.44054413}},"74367":{"cp":"74367","estado":"Puebla","municipio":"Atlixco","colonias":["Valle Real","Almazantla","Campestre San José","Rincón de San Agustín","Ex Hacienda San Agustín","Emiliano Zapata los Molinos","San Agustín de los Molinos","San Agustín Huixaxtla","Santa Cruz Tehuixpango","Tolometla de Benito Juárez"],"coords":{"lat":18.91709328,"lon":-98.396698}},"74368":{"cp":"74368","estado":"Puebla","municipio":"Atlixco","colonias":["Francisco Villa","Ex Hacienda San Félix","San Isidro","Texiquémetl (Los Olivares)","San Francisco Primo de Verdad","Diez de Abril","Ricardo Flores Magón","San José el Recreo","Lomas de San Juan Tejaluca","Emiliano Zapata Nexatengo","San Isidro Huilotepec","Juan Uvera","San Félix Almazán","San Félix Hidalgo","San Juan Portezuelo","Santa Ana Yancuitlalpan","Santa Lucia Cosamaloapan","Santo Domingo Atoyatempan"],"coords":{"lat":18.89614296,"lon":-98.39722443}},"74369":{"cp":"74369","estado":"Puebla","municipio":"Atlixco","colonias":["Otilio Montaño (La Concepción)","San Esteban Zoapiltepec","San Felipe Xonacayucan","San Jerónimo Caleras"],"coords":{"lat":18.85699654,"lon":-98.33470154}},"74370":{"cp":"74370","estado":"Puebla","municipio":"Huaquechula","colonias":["San Antonio Cuautla","Huaquechula","San Diego el Organal","San Juan Vallarta","Santiago Tetla"],"coords":{"lat":18.75715065,"lon":-98.53991699}},"74372":{"cp":"74372","estado":"Puebla","municipio":"Huaquechula","colonias":["Ahuatlán","Rancho Nuevo Michapita (Michapita)"],"coords":null},"74373":{"cp":"74373","estado":"Puebla","municipio":"Huaquechula","colonias":["Teacalco de Dorantes"],"coords":{"lat":18.80418587,"lon":-98.50979614}},"74374":{"cp":"74374","estado":"Puebla","municipio":"Huaquechula","colonias":["San Pedro Contla","Tlapetlahuaya"],"coords":{"lat":18.75471115,"lon":-98.57049561}},"74375":{"cp":"74375","estado":"Puebla","municipio":"Huaquechula","colonias":["Santa Cruz Yancuitlalpan","Del Fresnillo","Cacaloxúchitl","La Venta","Progreso","Soto y Gama"],"coords":{"lat":18.76164818,"lon":-98.4958725}},"74376":{"cp":"74376","estado":"Puebla","municipio":"Huaquechula","colonias":["El Paraíso","Mártir Cuauhtémoc","Santa Ana Coatepec"],"coords":{"lat":18.84469414,"lon":-98.44334412}},"74377":{"cp":"74377","estado":"Puebla","municipio":"Huaquechula","colonias":["San Juan Bautista","Champusco","San Juan Huiluco (Huiluco)","La Libertad","Soledad Morelos","Tronconal"],"coords":{"lat":18.83543015,"lon":-98.48591614}},"74378":{"cp":"74378","estado":"Puebla","municipio":"Huaquechula","colonias":["Emiliano Zapata (San Miguel)","Tezonteopan de Bonilla"],"coords":{"lat":18.74950027,"lon":-98.49156952}},"74379":{"cp":"74379","estado":"Puebla","municipio":"Huaquechula","colonias":["Huejotal","Morelos","San Lucas Matlala"],"coords":{"lat":18.6984787,"lon":-98.6005249}},"74380":{"cp":"74380","estado":"Puebla","municipio":"San Diego la Mesa Tochimiltzingo","colonias":["Tochimiltzingo"],"coords":{"lat":18.81060219,"lon":-98.33016205}},"74382":{"cp":"74382","estado":"Puebla","municipio":"San Diego la Mesa Tochimiltzingo","colonias":["San Bartolome Chimalhuacan"],"coords":{"lat":18.82593536,"lon":-98.25639343}},"74385":{"cp":"74385","estado":"Puebla","municipio":"San Diego la Mesa Tochimiltzingo","colonias":["La Soledad Tepehuaxtitla"],"coords":{"lat":18.79795265,"lon":-98.31847382}},"74389":{"cp":"74389","estado":"Puebla","municipio":"San Diego la Mesa Tochimiltzingo","colonias":["Guadalupe Amolocayan"],"coords":{"lat":18.70975113,"lon":-98.34190369}},"74390":{"cp":"74390","estado":"Puebla","municipio":"Tepeojuma","colonias":["Independencia","Tepeojuma"],"coords":{"lat":18.72553825,"lon":-98.44880676}},"74393":{"cp":"74393","estado":"Puebla","municipio":"Tepeojuma","colonias":["Teyuca"],"coords":{"lat":18.75501442,"lon":-98.44980621}},"74394":{"cp":"74394","estado":"Puebla","municipio":"Tepeojuma","colonias":["Xoyatla"],"coords":{"lat":18.75434685,"lon":-98.39176941}},"74395":{"cp":"74395","estado":"Puebla","municipio":"Tepeojuma","colonias":["El Astillero"],"coords":{"lat":18.69841385,"lon":-98.4096756}},"74397":{"cp":"74397","estado":"Puebla","municipio":"Tepeojuma","colonias":["La Magdalena"],"coords":{"lat":18.6934433,"lon":-98.38518524}}}