{"89600":{"cp":"89600","estado":"Tamaulipas","municipio":"Altamira","colonias":["Altamira Centro"],"coords":{"lat":22.39583397,"lon":-97.93704987}},"89602":{"cp":"89602","estado":"Tamaulipas","municipio":"Altamira","colonias":["Valles de España","Unidos Avanzamos","Encinos","Villas del Sol","Electricistas","Los Obeliscos","Los Mangos","Valle Real","El Abedul","Los Pinos","Jardín Real","Adolfo López Mateos","Alejandro Briones","Roger Gómez","Santo Domingo","Alameda","Altamira","Emilio Portes Gil","Enrique Cárdenas González","Fidel Velázquez","Felipe Carrillo Puerto","Guadalupe Victoria","Independencia","Las Blancas","Las Fuentes","Diana Laura Riojas de Colosio","León F Gual","Los Laureles","Los Mangos","Luis Donaldo Colosio","Las Margaritas","Nuevo México","Primavera Norte","Revolución Obrera","Santa Amalia","Tampiquito","20 de Noviembre","Campo Tamaulipas","César López de Lara","La Unión","Los Pinos","Los Presidentes","Martín A Martínez","El Nogal","Valle Verde","La Joya","Villerías","Educación","Álamo","Altamira Sector IV","Petrolera","El Pedregal","Lázaro Cárdenas","La Florida","Sección 3 Petroleros","María Antonieta Márquez","Los Placeres del Campo","El Repecho"],"coords":{"lat":22.42486954,"lon":-97.9397049}},"89603":{"cp":"89603","estado":"Tamaulipas","municipio":"Altamira","colonias":["Los Olivos","Las Alamedas","Santa Mónica","Parque de la Pequeña y Mediana Industria","Valle Esmeralda Residencial","El Roble","Comercial FIMEX","Andaluz","Palmares","Francisco I Madero","La Pedrera","Francisco Villa","Laguna de la Puerta","Magdaleno Aguilar","La Potosina","Corredor Industrial","Emiliano Zapata","José de Escandón","Fundadores","Industrial Guerrero","Jardines de Arboledas","Arrecifes","Municipios Libres","Paraíso","Unidad Satélite","Venustiano Carranza","Villas de Altamira","Villa de las Flores","Satélite Chapala","Villas del Sol","De los Ríos","Municipios Libres las Negras","San Jacinto","Villa las Rosas","Paseo Real","Las Palmas","Ricardo Flores Magón","Francisco Medrano","Las Adelitas","Colinas de Altamira","Las Haciendas","Los Prados","Hacienda las Palmas","Arboledas","Real Altamira","El Edén","Arecas","Puerto Industrial de Altamira"],"coords":{"lat":22.39369392,"lon":-97.88169861}},"89604":{"cp":"89604","estado":"Tamaulipas","municipio":"Altamira","colonias":["Valle Dorado","2 de Mayo","Miramar","Nuevo Tampico","Albañiles","Américo Villarreal","Bahía","Benito Juárez","El Mundo","El Triunfo","Habitacional","Jazmín","José María Morelos","Justo Sierra","Los Fresnos","Nuevo Madero","Nuevo Tampico Sector 2","Plomeros","San Arnoldo","Santa Elena","Serapio Venegas","Tamaulipas","El Contadero","Primavera","San Antonio","Santo Tomas","Guadalupe Cervantes","Gema","San Ángel","Ampliación el Contadero","Residencia Velamar","Dunas Doradas","La Esperanza","Cancún"],"coords":{"lat":22.33320808,"lon":-97.84657288}},"89605":{"cp":"89605","estado":"Tamaulipas","municipio":"Altamira","colonias":["Acapulquito","Sotavento","Punta Laguna","Agua de Castilla (La Bajada)","Españita","Ganadera","Tampico Altamira","Central de Abastos","Lagunas de Miralta","Vega de Esteros","Colinas de la Laguna","Huatulquito","Huatulco","Náutico Residencial","Floresta","Residencial Real Campestre","Loma Bonita","Villas Náutico"],"coords":{"lat":22.34183121,"lon":-97.88579559}},"89606":{"cp":"89606","estado":"Tamaulipas","municipio":"Altamira","colonias":["Canarios","Vista Laguna Residencial","Monte Alto Antiguo","Alejandro Briones","La Morita","Las Brisas","Las Flores","Loma Alta","Lomas de Altamira","Lomas de Valle Verde","Los Arados","Azteca","Los Encinos","Nuevo Lomas del Real","Lomas de Miralta","Lomas de Monte Alto","Lomas de Rosales","Juan Genaro de la Portilla","Colinas de Champayán","Rinconada de la Aurora","Los Encinos Residencial","Lomas Campestre","Monte Alto Sipobladur","Monte de los Olivos"],"coords":{"lat":22.36333847,"lon":-97.91439056}},"89607":{"cp":"89607","estado":"Tamaulipas","municipio":"Altamira","colonias":["Villa Diamante","Santa Clara","Campestre Laguna","Alameda","Enrique Cárdenas Centro","INFONAVIT Fidel Velázquez","Jardines de Altamira","Jardines de Champayán","La Florida","Las Grullas","Los Naranjos","Las Marismas","Revolución Verde","Los Sábalos","Santa Ana","Los Almendros","Pescadores I","Altamira II","Pescadores II","El Campanario","Puerto Escondido","Jardines de Altamira","Santa Anita","Ixtapa","Privada Santiago","Tercer Milenium","Laguna Florida","Villas de Champayán","Villas de Champayán 2"],"coords":{"lat":22.39312553,"lon":-97.94320679}},"89610":{"cp":"89610","estado":"Tamaulipas","municipio":"Altamira","colonias":["Cuauhtémoc","La Esperanza","Jardín","Magisterial"],"coords":{"lat":22.54362679,"lon":-98.14939117}},"89613":{"cp":"89613","estado":"Tamaulipas","municipio":"Altamira","colonias":["Santa Gertrudis"],"coords":{"lat":22.70817947,"lon":-98.28929138}},"89614":{"cp":"89614","estado":"Tamaulipas","municipio":"Altamira","colonias":["Graneros del Sur (Cuatrocientos Pueblos)","Mariano Matamoros","Santa Juana","San Antonio"],"coords":{"lat":22.67667961,"lon":-98.08705139}},"89615":{"cp":"89615","estado":"Tamaulipas","municipio":"Altamira","colonias":["José María Luis Mora (Las Margaritas)"],"coords":{"lat":22.65205765,"lon":-97.97154999}},"89620":{"cp":"89620","estado":"Tamaulipas","municipio":"Altamira","colonias":["Esteros"],"coords":{"lat":22.51586914,"lon":-98.12432098}},"89625":{"cp":"89625","estado":"Tamaulipas","municipio":"Altamira","colonias":["Providencia y Naranjos"],"coords":{"lat":22.52037048,"lon":-98.3059082}},"89630":{"cp":"89630","estado":"Tamaulipas","municipio":"Altamira","colonias":["Lomas del Real"],"coords":{"lat":22.56501961,"lon":-97.90475464}},"89632":{"cp":"89632","estado":"Tamaulipas","municipio":"Altamira","colonias":["Aquiles Serdán (El Barranco)"],"coords":{"lat":22.5643425,"lon":-97.90460968}},"89633":{"cp":"89633","estado":"Tamaulipas","municipio":"Altamira","colonias":["Ampliación el Arenal"],"coords":{"lat":22.53470612,"lon":-97.96150208}},"89635":{"cp":"89635","estado":"Tamaulipas","municipio":"Altamira","colonias":["Agua de Castilla"],"coords":{"lat":22.51216507,"lon":-97.96527863}},"89636":{"cp":"89636","estado":"Tamaulipas","municipio":"Altamira","colonias":["Miguel Hidalgo","Nuevo CERESO Regional de Altamira","Tres Marías","Benito Juárez"],"coords":{"lat":22.46666908,"lon":-98.03617859}},"89640":{"cp":"89640","estado":"Tamaulipas","municipio":"Altamira","colonias":["Cervantes"],"coords":{"lat":22.46804237,"lon":-98.09518433}},"89641":{"cp":"89641","estado":"Tamaulipas","municipio":"Altamira","colonias":["Maclovio Herrera (Miradores)"],"coords":{"lat":23.0642662,"lon":-99.4721756}},"89642":{"cp":"89642","estado":"Tamaulipas","municipio":"Altamira","colonias":["Santa Inés (Kilómetro 40)","Río Tamiahua"],"coords":{"lat":22.52880478,"lon":-98.07038879}},"89643":{"cp":"89643","estado":"Tamaulipas","municipio":"Altamira","colonias":["Mata del Abra"],"coords":{"lat":22.446558,"lon":-98.12710571}},"89644":{"cp":"89644","estado":"Tamaulipas","municipio":"Altamira","colonias":["El Fuerte"],"coords":{"lat":22.43198204,"lon":-98.09172821}},"89645":{"cp":"89645","estado":"Tamaulipas","municipio":"Altamira","colonias":["Tres de Mayo (Mata Negra)"],"coords":{"lat":22.39372253,"lon":-98.08042908}},"89650":{"cp":"89650","estado":"Tamaulipas","municipio":"Altamira","colonias":["La Colonia (Estación Colonias)"],"coords":{"lat":22.44104767,"lon":-98.01567078}},"89670":{"cp":"89670","estado":"Tamaulipas","municipio":"Aldama","colonias":["Santa Martha","El Lucero","Del Valle","Jesús Vega","Los Ébanos","Los Encinos","Olimpia de la Garza","Paraíso","Santa Elvira","Santa Isabel","Tamasopo","Valores","Aldama","Francisco I Madero","La Azufrosa (El Higuerón)","Arboledas","Brownsville","Constitución","Del Bosque","Los Pinos","Luis Caballero","Matamoros","Revolución Verde","Río Verde","Nuevo Tamaulipas"],"coords":{"lat":22.92124939,"lon":-98.08474731}},"89672":{"cp":"89672","estado":"Tamaulipas","municipio":"Aldama","colonias":["Las Flores","Morón"],"coords":{"lat":22.72754478,"lon":-97.86454773}},"89673":{"cp":"89673","estado":"Tamaulipas","municipio":"Aldama","colonias":["El Carrizal (Carrera Torres)","El Carrizal Segundo","Higinio Tanguma"],"coords":{"lat":22.70851326,"lon":-98.24208832}},"89674":{"cp":"89674","estado":"Tamaulipas","municipio":"Aldama","colonias":["Rancho de Piedra","Revolución"],"coords":{"lat":22.68750954,"lon":-97.88111877}},"89675":{"cp":"89675","estado":"Tamaulipas","municipio":"Aldama","colonias":["El Real Viejo","Santa María"],"coords":{"lat":22.95480537,"lon":-98.17718506}},"89676":{"cp":"89676","estado":"Tamaulipas","municipio":"Aldama","colonias":["Barra del Tordo","Francisco Villa (Pancho Villa)","El Pichijumo"],"coords":{"lat":22.91188431,"lon":-98.03276825}},"89677":{"cp":"89677","estado":"Tamaulipas","municipio":"Aldama","colonias":["El Olivo","Las Yucas","La Cabecera"],"coords":{"lat":23.13482094,"lon":-98.23136139}},"89678":{"cp":"89678","estado":"Tamaulipas","municipio":"Aldama","colonias":["Buenavista","Nuevo Progreso (La Gaviota)"],"coords":{"lat":23.19507408,"lon":-97.8503418}},"89679":{"cp":"89679","estado":"Tamaulipas","municipio":"Aldama","colonias":["El Vidal","Las Alazanas"],"coords":{"lat":23.34346199,"lon":-98.13564301}},"89693":{"cp":"89693","estado":"Tamaulipas","municipio":"Tampico","colonias":["La Isleta (Río Tamesí)","Isleta Vicente Díaz del Ángel","Isleta Guillermo Sandoval Ruiz"],"coords":null}}