{"92900":{"cp":"92900","estado":"Veracruz de Ignacio de la Llave","municipio":"Tihuatlán","colonias":["El Águila","La Isla (Kilómetro 10)","Rancho Nuevo","Xocotla"],"coords":{"lat":20.58098412,"lon":-97.48864746}},"92903":{"cp":"92903","estado":"Veracruz de Ignacio de la Llave","municipio":"Tihuatlán","colonias":["Acontitla","San Miguel Mecatepec"],"coords":{"lat":20.66922951,"lon":-97.37554169}},"92904":{"cp":"92904","estado":"Veracruz de Ignacio de la Llave","municipio":"Tihuatlán","colonias":["Enrique Rodríguez Cano (Zapotalillo)","Chichicoaxtla"],"coords":{"lat":20.65880966,"lon":-97.48987579}},"92905":{"cp":"92905","estado":"Veracruz de Ignacio de la Llave","municipio":"Tihuatlán","colonias":["La Concepción"],"coords":{"lat":20.66004562,"lon":-97.41391754}},"92906":{"cp":"92906","estado":"Veracruz de Ignacio de la Llave","municipio":"Tihuatlán","colonias":["Paso Del Pital"],"coords":{"lat":20.62867165,"lon":-97.41870117}},"92907":{"cp":"92907","estado":"Veracruz de Ignacio de la Llave","municipio":"Tihuatlán","colonias":["El Palmar","Úrsulo Galván"],"coords":{"lat":20.60674667,"lon":-97.42951202}},"92909":{"cp":"92909","estado":"Veracruz de Ignacio de la Llave","municipio":"Tihuatlán","colonias":["Poza Rica (El Tajín)"],"coords":{"lat":20.55286407,"lon":-97.47049713}},"92910":{"cp":"92910","estado":"Veracruz de Ignacio de la Llave","municipio":"Tihuatlán","colonias":["Emiliano Zapata (La Bomba)","Del Sol","El Mamey","El Manantial","Hidalgo","Francisco I. Madero"],"coords":{"lat":20.55130386,"lon":-97.52358246}},"92911":{"cp":"92911","estado":"Veracruz de Ignacio de la Llave","municipio":"Tihuatlán","colonias":["Buena Vista","Acuatempa","Nuevo Progreso"],"coords":{"lat":20.61566734,"lon":-97.505867}},"92912":{"cp":"92912","estado":"Veracruz de Ignacio de la Llave","municipio":"Tihuatlán","colonias":["Plan de Ayala"],"coords":{"lat":20.5516758,"lon":-97.47608948}},"92913":{"cp":"92913","estado":"Veracruz de Ignacio de la Llave","municipio":"Tihuatlán","colonias":["El Copal","Sebastián Lerdo de Tejada","Papatlarillo","San Pedro Miahuapan"],"coords":{"lat":20.64159966,"lon":-97.58210754}},"92914":{"cp":"92914","estado":"Veracruz de Ignacio de la Llave","municipio":"Tihuatlán","colonias":["Antonio M. Quirasco","Constitución","Palo de Rosa"],"coords":{"lat":20.5682621,"lon":-97.67849731}},"92915":{"cp":"92915","estado":"Veracruz de Ignacio de la Llave","municipio":"Tihuatlán","colonias":["Poza Azul de los Reyes","Progreso de Maravillas"],"coords":{"lat":20.60336494,"lon":-97.68079376}},"92916":{"cp":"92916","estado":"Veracruz de Ignacio de la Llave","municipio":"Tihuatlán","colonias":["El Huizotate"],"coords":{"lat":20.5861454,"lon":-97.52801514}},"92917":{"cp":"92917","estado":"Veracruz de Ignacio de la Llave","municipio":"Tihuatlán","colonias":["Sector Cuatro","General Lázaro Cárdenas del Río","Ricardo Flores Magón","Totolapa","Lindero","Fredepo","Manantial","Zacate Colorado","Santa Isabel","Dirección de Caminos","Sector Cinco","Sector Pajaritos","Sector Ceiba","Sector México"],"coords":{"lat":20.56029701,"lon":-97.47669983}},"92920":{"cp":"92920","estado":"Veracruz de Ignacio de la Llave","municipio":"Tihuatlán","colonias":["Tierra Blanca"],"coords":{"lat":20.71163177,"lon":-97.52690125}},"92922":{"cp":"92922","estado":"Veracruz de Ignacio de la Llave","municipio":"Tihuatlán","colonias":["La Reforma"],"coords":{"lat":20.68303108,"lon":-97.53714752}},"92923":{"cp":"92923","estado":"Veracruz de Ignacio de la Llave","municipio":"Tihuatlán","colonias":["Pueblo Viejo","Jiliapa Segundo","San Nicolás"],"coords":{"lat":20.68836021,"lon":-97.60161591}},"92925":{"cp":"92925","estado":"Veracruz de Ignacio de la Llave","municipio":"Tihuatlán","colonias":["Tecomate"],"coords":{"lat":20.74806786,"lon":-97.56715393}},"92926":{"cp":"92926","estado":"Veracruz de Ignacio de la Llave","municipio":"Tihuatlán","colonias":["El Terrero"],"coords":{"lat":20.79895782,"lon":-97.564888}},"92927":{"cp":"92927","estado":"Veracruz de Ignacio de la Llave","municipio":"Tihuatlán","colonias":["Zapotal Santa Cruz","Tumbadero"],"coords":{"lat":20.84805298,"lon":-97.47373199}},"92928":{"cp":"92928","estado":"Veracruz de Ignacio de la Llave","municipio":"Tihuatlán","colonias":["La Pasadita","El Horcón"],"coords":{"lat":20.73092651,"lon":-97.49305725}},"92929":{"cp":"92929","estado":"Veracruz de Ignacio de la Llave","municipio":"Tihuatlán","colonias":["Chapolhuac","Chichimantla Segundo","La Unión Segundo"],"coords":{"lat":20.71762848,"lon":-97.52958679}},"92930":{"cp":"92930","estado":"Veracruz de Ignacio de la Llave","municipio":"Tihuatlán","colonias":["Tihuatlán Centro"],"coords":{"lat":20.71298409,"lon":-97.53633118}},"92933":{"cp":"92933","estado":"Veracruz de Ignacio de la Llave","municipio":"Tihuatlán","colonias":["Unidad Nacional","Socialistas","Lázaro Cárdenas"],"coords":{"lat":20.72675514,"lon":-97.52732086}},"92934":{"cp":"92934","estado":"Veracruz de Ignacio de la Llave","municipio":"Tihuatlán","colonias":["Azteca","Magisterial"],"coords":{"lat":20.70438766,"lon":-97.53368378}},"92935":{"cp":"92935","estado":"Veracruz de Ignacio de la Llave","municipio":"Tihuatlán","colonias":["Cruz Blanca"],"coords":{"lat":20.71500015,"lon":-97.53829193}},"92936":{"cp":"92936","estado":"Veracruz de Ignacio de la Llave","municipio":"Tihuatlán","colonias":["Independencia","Benito Juárez","San Francisco de Asís"],"coords":{"lat":20.71888924,"lon":-97.54347229}},"92937":{"cp":"92937","estado":"Veracruz de Ignacio de la Llave","municipio":"Tihuatlán","colonias":["Totomoxtte","Tepetate","Lomas del Paraíso","Lomas Verdes"],"coords":{"lat":20.72712517,"lon":-97.54196167}},"92940":{"cp":"92940","estado":"Veracruz de Ignacio de la Llave","municipio":"Castillo de Teayo","colonias":["La Lima Nueva","Castillo de Teayo","La Guadalupe","Teayo"],"coords":{"lat":20.74219131,"lon":-97.64089203}},"92941":{"cp":"92941","estado":"Veracruz de Ignacio de la Llave","municipio":"Castillo de Teayo","colonias":["Paso de Valencia","Mequetla","El Bejucal"],"coords":{"lat":20.79694748,"lon":-97.68890381}},"92942":{"cp":"92942","estado":"Veracruz de Ignacio de la Llave","municipio":"Castillo de Teayo","colonias":["Nuevo Jalisco","Moralillo","El Nuevo Naranjal (Las Carmelitas)","El Naranjal","Arely"],"coords":null},"92943":{"cp":"92943","estado":"Veracruz de Ignacio de la Llave","municipio":"Castillo de Teayo","colonias":["El Xúchitl","Francisco Luján Adame (El Totomoxcle)","Nueva Reforma","El Pital","Francisco Luján Adame (Dos Pasos)"],"coords":{"lat":20.74944878,"lon":-97.62997437}},"92944":{"cp":"92944","estado":"Veracruz de Ignacio de la Llave","municipio":"Castillo de Teayo","colonias":["Las Camelias","La Defensa"],"coords":null},"92945":{"cp":"92945","estado":"Veracruz de Ignacio de la Llave","municipio":"Castillo de Teayo","colonias":["La Gloria","La Puerta"],"coords":null},"92946":{"cp":"92946","estado":"Veracruz de Ignacio de la Llave","municipio":"Castillo de Teayo","colonias":["El Ojital"],"coords":null},"92947":{"cp":"92947","estado":"Veracruz de Ignacio de la Llave","municipio":"Castillo de Teayo","colonias":["Pueblo Viejo (El Naranjal)","Ignacio Zaragoza"],"coords":null},"92948":{"cp":"92948","estado":"Veracruz de Ignacio de la Llave","municipio":"Castillo de Teayo","colonias":["Paso de las Flores","Santa Cruz","Palma Real"],"coords":null},"92949":{"cp":"92949","estado":"Veracruz de Ignacio de la Llave","municipio":"Castillo de Teayo","colonias":["Lima Vieja","La Esperanza Vieja"],"coords":null},"92970":{"cp":"92970","estado":"Veracruz de Ignacio de la Llave","municipio":"Cazones de Herrera","colonias":["Ojo de Agua","Limón Chiquito"],"coords":{"lat":20.71956635,"lon":-97.28141785}},"92972":{"cp":"92972","estado":"Veracruz de Ignacio de la Llave","municipio":"Cazones de Herrera","colonias":["Coyol Norte","Marco Antonio Muñoz (El Chaparral)","El Ramal"],"coords":null},"92973":{"cp":"92973","estado":"Veracruz de Ignacio de la Llave","municipio":"Cazones de Herrera","colonias":["San Román Chiquito (Anexo Morisco Número Dos)","La Ceiba"],"coords":{"lat":20.76799011,"lon":-97.24018097}},"92974":{"cp":"92974","estado":"Veracruz de Ignacio de la Llave","municipio":"Cazones de Herrera","colonias":["Morisco Número Uno (San Román Grande)","La Reforma de Herrera (Kilómetro 19)","Vega de Progreso","La Encantada","Manlio Fabio Altamirano Km. 25"],"coords":{"lat":20.73205757,"lon":-97.26105499}},"92975":{"cp":"92975","estado":"Veracruz de Ignacio de la Llave","municipio":"Cazones de Herrera","colonias":["Cruz Blanca Número Dos","Emiliano Zapata","Plan de Limón","Cabellal Número Uno","Cruz Blanca Número Uno"],"coords":{"lat":20.67573929,"lon":-97.32431793}},"92976":{"cp":"92976","estado":"Veracruz de Ignacio de la Llave","municipio":"Cazones de Herrera","colonias":["El Zapote","La Piedad","La Curva"],"coords":{"lat":20.67869759,"lon":-97.34060669}},"92977":{"cp":"92977","estado":"Veracruz de Ignacio de la Llave","municipio":"Cazones de Herrera","colonias":["El Marino","General Felipe Ángeles","Nuevo Tejamanil","Paso de Cazones","La Unión (Kilómetro 31)"],"coords":{"lat":20.72336769,"lon":-97.39195251}},"92978":{"cp":"92978","estado":"Veracruz de Ignacio de la Llave","municipio":"Cazones de Herrera","colonias":["El Sauce","Naranjos de Afuera (Naranjos Kilómetro 27)"],"coords":null},"92979":{"cp":"92979","estado":"Veracruz de Ignacio de la Llave","municipio":"Cazones de Herrera","colonias":["Cabellal Número Tres","Cabellal Número Dos","El Calichar"],"coords":null},"92980":{"cp":"92980","estado":"Veracruz de Ignacio de la Llave","municipio":"Cazones de Herrera","colonias":["Cazones de Herrera Centro"],"coords":{"lat":20.70732307,"lon":-97.31060791}},"92983":{"cp":"92983","estado":"Veracruz de Ignacio de la Llave","municipio":"Cazones de Herrera","colonias":["Alto Lucero"],"coords":{"lat":20.70514297,"lon":-97.3059845}},"92984":{"cp":"92984","estado":"Veracruz de Ignacio de la Llave","municipio":"Cazones de Herrera","colonias":["El Paraíso"],"coords":{"lat":20.69976616,"lon":-97.30531311}},"92985":{"cp":"92985","estado":"Veracruz de Ignacio de la Llave","municipio":"Cazones de Herrera","colonias":["El Huarache","El Progreso","La Antena","Agustin Acosta Lagunes"],"coords":{"lat":20.69892502,"lon":-97.31174469}},"92987":{"cp":"92987","estado":"Veracruz de Ignacio de la Llave","municipio":"Cazones de Herrera","colonias":["Cerro Del Fortín"],"coords":{"lat":20.70422935,"lon":-97.31231689}},"92990":{"cp":"92990","estado":"Veracruz de Ignacio de la Llave","municipio":"Cazones de Herrera","colonias":["Rancho Nuevo","Cerro Verde"],"coords":{"lat":20.67227173,"lon":-97.2064743}},"92992":{"cp":"92992","estado":"Veracruz de Ignacio de la Llave","municipio":"Cazones de Herrera","colonias":["Los Migueles"],"coords":null},"92993":{"cp":"92993","estado":"Veracruz de Ignacio de la Llave","municipio":"Cazones de Herrera","colonias":["Las Palmas","El Torno","Chaca Gorda"],"coords":null},"92994":{"cp":"92994","estado":"Veracruz de Ignacio de la Llave","municipio":"Cazones de Herrera","colonias":["Buenavista","Playa Azul","Barra de Cazones"],"coords":{"lat":20.72626686,"lon":-97.20741272}}}